MANIFEST.in
setup.cfg
setup.py
versioneer.py
frisk/__init__.py
frisk/__main__.py
frisk/_version.py
frisk/tsne.py
frisk.egg-info/PKG-INFO
frisk.egg-info/SOURCES.txt
frisk.egg-info/dependency_links.txt
frisk.egg-info/entry_points.txt
frisk.egg-info/requires.txt
frisk.egg-info/top_level.txt