Metadata-Version: 1.1
Name: frisk
Version: 0.1.10
Summary: 
